{"version":3,"kind":"Notebook","sha256":"bea26f043d93386d2e8191fbdccbdfa80793614d7d509d000b28bc576cc1e530","slug":"notebooks.ch1-introduction","location":"/notebooks/ch1_Introduction.ipynb","dependencies":[],"frontmatter":{"title":"Chapter 1: Multi Radar/ Multi Sensor (MRMS) System: Overview, Case Studies, and More!","content_includes_title":false,"kernelspec":{"name":"python3","display_name":"Python 3 (ipykernel)","language":"python"},"authors":[{"nameParsed":{"literal":"Ty Janoski","given":"Ty","family":"Janoski"},"name":"Ty Janoski","orcid":"0000-0003-4344-355X","affiliations":["City College of New York and NOAA/OAR National Severe Storms Laboratory"],"id":"contributors-myst-generated-uid-0"},{"nameParsed":{"literal":"Mya Sears","given":"Mya","family":"Sears"},"name":"Mya Sears","orcid":"0009-0003-5870-7498","affiliations":["NSF National Center for Atmospheric Research"],"id":"contributors-myst-generated-uid-1"},{"nameParsed":{"literal":"Bella Condo","given":"Bella","family":"Condo"},"name":"Bella Condo","orcid":"0009-0000-0688-7077","affiliations":["University at Albany (State University of New York)"],"id":"contributors-myst-generated-uid-2"},{"nameParsed":{"literal":"JD Heaton","given":"JD","family":"Heaton"},"name":"JD Heaton","orcid":"0009-0005-7424-4889","affiliations":["Metropolitan State University of Denver"],"id":"contributors-myst-generated-uid-3"},{"nameParsed":{"literal":"MaKenna Collins","given":"MaKenna","family":"Collins"},"name":"MaKenna Collins","orcid":"0009-0003-5566-3370","affiliations":["Jackson State University"],"id":"contributors-myst-generated-uid-4"},{"nameParsed":{"literal":"Maxwell Grover","given":"Maxwell","family":"Grover"},"name":"Maxwell Grover","orcid":"0000-0002-0370-8974","affiliations":["Argonne National Laboratory"],"id":"contributors-myst-generated-uid-5"}],"open_access":true,"license":{"content":{"id":"CC-BY-4.0","url":"https://creativecommons.org/licenses/by/4.0/","name":"Creative Commons Attribution 4.0 International","free":true,"CC":true},"code":{"id":"Apache-2.0","url":"https://opensource.org/licenses/Apache-2.0","name":"Apache License 2.0","free":true,"osi":true}},"github":"https://github.com/projectpythia/mrms-cookbook","copyright":"2025","affiliations":[{"id":"City College of New York and NOAA/OAR National Severe Storms Laboratory","name":"City College of New York and NOAA/OAR National Severe Storms Laboratory"},{"id":"NSF National Center for Atmospheric Research","name":"NSF National Center for Atmospheric Research"},{"id":"University at Albany (State University of New York)","name":"University at Albany (State University of New York)"},{"id":"Metropolitan State University of Denver","name":"Metropolitan State University of Denver"},{"id":"Jackson State University","name":"Jackson State University"},{"id":"Argonne National Laboratory","name":"Argonne National Laboratory"},{"id":"UAlbany","name":"University at Albany (SUNY)","department":"Atmospheric and Environmental Sciences","url":"https://www.albany.edu/daes"},{"id":"CISL","name":"NSF National Center for Atmospheric Research","department":"Computational and Information Systems Lab","url":"https://www.cisl.ucar.edu"},{"id":"Unidata","name":"NSF Unidata","url":"https://www.unidata.ucar.edu"},{"id":"Argonne","name":"Argonne National Laboratory","department":"Environmental Science Division","url":"https://www.anl.gov/evs"},{"id":"CarbonPlan","name":"CarbonPlan","url":"https://carbonplan.org"},{"id":"NVIDIA","name":"NVIDIA Corporation","url":"https://www.nvidia.com/"}],"source_url":"https://github.com/projectpythia/mrms-cookbook/blob/main/notebooks/ch1_Introduction.ipynb","edit_url":"https://github.com/projectpythia/mrms-cookbook/edit/main/notebooks/ch1_Introduction.ipynb","exports":[{"format":"ipynb","filename":"ch1_Introduction.ipynb","url":"/mrms-cookbook/build/ch1_Introduction-45bb31b5036d6050beba5c7cdc5e930f.ipynb"}]},"widgets":{},"mdast":{"type":"root","children":[{"type":"block","kind":"notebook-content","children":[{"type":"thematicBreak","position":{"start":{"line":1,"column":1},"end":{"line":1,"column":1}},"key":"sAwi2QEIQq"}],"key":"jySMDnmVFA"},{"type":"block","kind":"notebook-content","children":[{"type":"heading","depth":2,"position":{"start":{"line":1,"column":1},"end":{"line":1,"column":1}},"children":[{"type":"text","value":"Overview","position":{"start":{"line":1,"column":1},"end":{"line":1,"column":1}},"key":"tlYPAaKdh0"}],"identifier":"overview","label":"Overview","html_id":"overview","implicit":true,"key":"pJuDuRjI9H"},{"type":"paragraph","position":{"start":{"line":2,"column":1},"end":{"line":2,"column":1}},"children":[{"type":"text","value":"This notebook introduces users to MRMS, informs users on MRMS data sources, shows useful websites, and provides context on variable names. Follow through the notebook to learn more about MRMS and ways it can be used to aid in your research and decision-making!","position":{"start":{"line":2,"column":1},"end":{"line":2,"column":1}},"key":"ROLuOk7ymD"}],"key":"uhscz6zHEj"}],"key":"ED4chGa0RY"},{"type":"block","kind":"notebook-content","children":[{"type":"thematicBreak","position":{"start":{"line":1,"column":1},"end":{"line":1,"column":1}},"key":"YvlYrHIwbr"}],"key":"z1QpJ2tNN8"},{"type":"block","kind":"notebook-content","children":[{"type":"heading","depth":2,"position":{"start":{"line":1,"column":1},"end":{"line":1,"column":1}},"children":[{"type":"text","value":"MRMS System Overview","position":{"start":{"line":1,"column":1},"end":{"line":1,"column":1}},"key":"CcoWwJ6Mza"}],"identifier":"mrms-system-overview","label":"MRMS System Overview","html_id":"mrms-system-overview","implicit":true,"key":"ikP4OyHlZw"}],"key":"MMhlMGroyt"},{"type":"block","kind":"notebook-content","children":[{"type":"heading","depth":3,"position":{"start":{"line":1,"column":1},"end":{"line":1,"column":1}},"children":[{"type":"text","value":"What is MRMS?","position":{"start":{"line":1,"column":1},"end":{"line":1,"column":1}},"key":"lZQkmJ9Suu"}],"identifier":"what-is-mrms","label":"What is MRMS?","html_id":"what-is-mrms","implicit":true,"key":"yLZdmNzHE2"},{"type":"paragraph","position":{"start":{"line":2,"column":1},"end":{"line":2,"column":1}},"children":[{"type":"text","value":"The Multi-Radar/ Multi-Sensor (MRMS) System is a radar system developed by the National Severe Storms Laboratory (NSSL) that integrates data from satellites, radars, numerical prediction models, rain gauges, observations, and lightning reports into a standardized grid. Its goal is to provide smooth, high-resolution, and consistent weather products to inform decision-support services, aviation, transportation, numerical weather forecasting, hydrology, and public messaging.","position":{"start":{"line":2,"column":1},"end":{"line":2,"column":1}},"key":"cXlqhuk7Kv"}],"key":"zvqcYz1IRt"},{"type":"paragraph","position":{"start":{"line":4,"column":1},"end":{"line":4,"column":1}},"children":[{"type":"text","value":"Key features include:","position":{"start":{"line":4,"column":1},"end":{"line":4,"column":1}},"key":"cxs6IFlje2"}],"key":"ZAEnfTWyQQ"},{"type":"list","ordered":false,"spread":false,"position":{"start":{"line":5,"column":1},"end":{"line":8,"column":1}},"children":[{"type":"listItem","spread":true,"position":{"start":{"line":5,"column":1},"end":{"line":5,"column":1}},"children":[{"type":"paragraph","children":[{"type":"text","value":"3D radar mosaics","position":{"start":{"line":5,"column":1},"end":{"line":5,"column":1}},"key":"IUxvXoPtGo"}],"key":"r3yRhZsHKu"}],"key":"IMmEJz5vvw"},{"type":"listItem","spread":true,"position":{"start":{"line":6,"column":1},"end":{"line":6,"column":1}},"children":[{"type":"paragraph","children":[{"type":"text","value":"1-km x 2-minute update cycle","position":{"start":{"line":6,"column":1},"end":{"line":6,"column":1}},"key":"xNau16L7eB"}],"key":"HxOvLSvMuU"}],"key":"cor44dXsyu"},{"type":"listItem","spread":true,"position":{"start":{"line":7,"column":1},"end":{"line":7,"column":1}},"children":[{"type":"paragraph","children":[{"type":"text","value":"Severe weather and aviation products","position":{"start":{"line":7,"column":1},"end":{"line":7,"column":1}},"key":"A89xQHy3QY"}],"key":"TIka9BMzvz"}],"key":"by3rVe03hD"},{"type":"listItem","spread":true,"position":{"start":{"line":8,"column":1},"end":{"line":8,"column":1}},"children":[{"type":"paragraph","children":[{"type":"text","value":"Covers CONUS, Alaska, Hawaii, (parts of) the Caribbean, Guam, and parts of southern Canada","position":{"start":{"line":8,"column":1},"end":{"line":8,"column":1}},"key":"lnLJGJ6nSR"}],"key":"BB71ENXFGw"}],"key":"StxXPnsX5n"}],"key":"dnn15CUSxr"}],"key":"l74lHfE8kF"},{"type":"block","kind":"notebook-content","children":[{"type":"heading","depth":3,"position":{"start":{"line":1,"column":1},"end":{"line":1,"column":1}},"children":[{"type":"text","value":"MRMS Data Sources","position":{"start":{"line":1,"column":1},"end":{"line":1,"column":1}},"key":"Xy9az454Lr"}],"identifier":"mrms-data-sources","label":"MRMS Data Sources","html_id":"mrms-data-sources","implicit":true,"key":"VRgLRCXi1o"},{"type":"paragraph","position":{"start":{"line":2,"column":1},"end":{"line":2,"column":1}},"children":[{"type":"text","value":"The MRMS integrates data from various sources to produce advanced weather products.","position":{"start":{"line":2,"column":1},"end":{"line":2,"column":1}},"key":"x7FBSx1WW9"}],"key":"saimNe3m88"},{"type":"list","ordered":false,"spread":false,"position":{"start":{"line":4,"column":1},"end":{"line":9,"column":1}},"children":[{"type":"listItem","spread":true,"position":{"start":{"line":4,"column":1},"end":{"line":4,"column":1}},"children":[{"type":"paragraph","children":[{"type":"text","value":"Radars: Weather Surveillance Radar (WSR-88D), Canadian radar networks, Terminal Doppler Weather Radars (TDWRs), commercial radars, and more.","position":{"start":{"line":4,"column":1},"end":{"line":4,"column":1}},"key":"JeuWKKA8np"}],"key":"rDF1eA4noH"}],"key":"I3Yuot7ldv"},{"type":"listItem","spread":true,"position":{"start":{"line":5,"column":1},"end":{"line":5,"column":1}},"children":[{"type":"paragraph","children":[{"type":"text","value":"Satellite: Geostationary Operational Environmental Satellite (GOES). Provides continuous data on atmospheric conditions.","position":{"start":{"line":5,"column":1},"end":{"line":5,"column":1}},"key":"DxKuyo6Pix"}],"key":"QrJpsJ05LY"}],"key":"yv0KEMzv7T"},{"type":"listItem","spread":true,"position":{"start":{"line":6,"column":1},"end":{"line":6,"column":1}},"children":[{"type":"paragraph","children":[{"type":"text","value":"Numerical prediction models: High Resolution Rapid Refresh (HRRR), Rapid Refresh (RAP).","position":{"start":{"line":6,"column":1},"end":{"line":6,"column":1}},"key":"LugxXl2z0l"}],"key":"gHdHDVVzip"}],"key":"nrXI52kizM"},{"type":"listItem","spread":true,"position":{"start":{"line":7,"column":1},"end":{"line":7,"column":1}},"children":[{"type":"paragraph","children":[{"type":"text","value":"Surface observations","position":{"start":{"line":7,"column":1},"end":{"line":7,"column":1}},"key":"bp7znvDZuB"}],"key":"dIdaIqF5wH"}],"key":"klKc8bUhCm"},{"type":"listItem","spread":true,"position":{"start":{"line":8,"column":1},"end":{"line":8,"column":1}},"children":[{"type":"paragraph","children":[{"type":"text","value":"Rain gauges: approximately 7,000 hourly rain gauge sensors, Hydrometeorological Automated Data System (HADS)","position":{"start":{"line":8,"column":1},"end":{"line":8,"column":1}},"key":"mTPLzWu67x"}],"key":"Ln93qGIiir"}],"key":"qkycNMbHuK"},{"type":"listItem","spread":true,"position":{"start":{"line":9,"column":1},"end":{"line":9,"column":1}},"children":[{"type":"paragraph","children":[{"type":"text","value":"Lightning reports: National Lightning Detection Network (NLDN)","position":{"start":{"line":9,"column":1},"end":{"line":9,"column":1}},"key":"JRyR5nBFSn"}],"key":"GEpJg1bQUd"}],"key":"ZbAjS7e6ih"}],"key":"Yg2jgeV8MT"}],"key":"QEeRqxGYre"},{"type":"block","kind":"notebook-content","children":[{"type":"heading","depth":3,"position":{"start":{"line":1,"column":1},"end":{"line":1,"column":1}},"children":[{"type":"text","value":"AWS Structure & Access","position":{"start":{"line":1,"column":1},"end":{"line":1,"column":1}},"key":"oi2B8u4YQF"}],"identifier":"aws-structure-access","label":"AWS Structure & Access","html_id":"aws-structure-access","implicit":true,"key":"vzD7zkYEmY"},{"type":"paragraph","position":{"start":{"line":3,"column":1},"end":{"line":3,"column":1}},"children":[{"type":"text","value":"To meet the demand for accessible, scalable, reliable, and timely data, MRMS hosts its data on Amazon Web Services (AWS).","position":{"start":{"line":3,"column":1},"end":{"line":3,"column":1}},"key":"dzxhHlxzIA"}],"key":"gBw4dwR0ns"},{"type":"paragraph","position":{"start":{"line":5,"column":1},"end":{"line":5,"column":1}},"children":[{"type":"text","value":"Accessing NOAA MRMS data on AWS is simple. ","position":{"start":{"line":5,"column":1},"end":{"line":5,"column":1}},"key":"HZLtjkMd2Q"},{"type":"link","url":"https://noaa-mrms-pds.s3.amazonaws.com/index.html","position":{"start":{"line":5,"column":1},"end":{"line":5,"column":1}},"children":[{"type":"text","value":"Just click this link to navigate to the dedicated MRMS suite on AWS","position":{"start":{"line":5,"column":1},"end":{"line":5,"column":1}},"key":"SGX1nETXYJ"}],"urlSource":"https://noaa-mrms-pds.s3.amazonaws.com/index.html","key":"rDHmuTVGqr"},{"type":"text","value":", select your area of interest, e.g., Alaska, CONUS, Hawaii, etc., then select the variable(s) you wish to study.","position":{"start":{"line":5,"column":1},"end":{"line":5,"column":1}},"key":"kLHpTVwYjZ"}],"key":"uzPR48VD6H"},{"type":"paragraph","position":{"start":{"line":7,"column":1},"end":{"line":7,"column":1}},"children":[{"type":"text","value":"The next section talks more about some of the variables available and what they are.","position":{"start":{"line":7,"column":1},"end":{"line":7,"column":1}},"key":"JAqAE45Xh7"}],"key":"hwAxXUOpf6"}],"key":"pqBG3sel59"},{"type":"block","kind":"notebook-content","children":[{"type":"heading","depth":3,"position":{"start":{"line":1,"column":1},"end":{"line":1,"column":1}},"children":[{"type":"text","value":"MRMS Naming","position":{"start":{"line":1,"column":1},"end":{"line":1,"column":1}},"key":"W2Fk8jllPG"}],"identifier":"mrms-naming","label":"MRMS Naming","html_id":"mrms-naming","implicit":true,"key":"ubrm7EnEyT"},{"type":"paragraph","position":{"start":{"line":3,"column":1},"end":{"line":3,"column":1}},"children":[{"type":"text","value":"The MRMS has a wide range of variables you can use for your research and operations. ","position":{"start":{"line":3,"column":1},"end":{"line":3,"column":1}},"key":"sIa1ncFTRs"},{"type":"link","url":"https://www.nssl.noaa.gov/projects/mrms/operational/tables.php","position":{"start":{"line":3,"column":1},"end":{"line":3,"column":1}},"children":[{"type":"text","value":"By clicking here","position":{"start":{"line":3,"column":1},"end":{"line":3,"column":1}},"key":"PYP5npNjxw"}],"urlSource":"https://www.nssl.noaa.gov/projects/mrms/operational/tables.php","key":"XP42aJL1qo"},{"type":"text","value":", you can find the Operational MRMS GRIB2 Tables that detail the name of a dataset, frequencies, what unit the data is measured in, missing data, range folded, instances of no coverage, a description, and a notes column.","position":{"start":{"line":3,"column":1},"end":{"line":3,"column":1}},"key":"Tw8AfB5ClA"}],"key":"IgHoCdTQxK"},{"type":"paragraph","position":{"start":{"line":5,"column":1},"end":{"line":5,"column":1}},"children":[{"type":"text","value":"In this Cookbook, we use the following variables:","position":{"start":{"line":5,"column":1},"end":{"line":5,"column":1}},"key":"J85mX0DPVX"}],"key":"WWptuJJCtB"},{"type":"table","position":{"start":{"line":7,"column":1},"end":{"line":18,"column":1}},"children":[{"type":"tableRow","position":{"start":{"line":7,"column":1},"end":{"line":7,"column":1}},"children":[{"type":"tableCell","header":true,"position":{"start":{"line":7,"column":1},"end":{"line":7,"column":1}},"children":[{"type":"text","value":"Variable","position":{"start":{"line":7,"column":1},"end":{"line":7,"column":1}},"key":"t6K4SLBPjc"}],"key":"so3qIWGxOU"},{"type":"tableCell","header":true,"position":{"start":{"line":7,"column":1},"end":{"line":7,"column":1}},"children":[{"type":"text","value":"Description","position":{"start":{"line":7,"column":1},"end":{"line":7,"column":1}},"key":"qGWXji21Q0"}],"key":"LUunpFHcO3"}],"key":"fQlaUZHqXh"},{"type":"tableRow","position":{"start":{"line":9,"column":1},"end":{"line":9,"column":1}},"children":[{"type":"tableCell","position":{"start":{"line":9,"column":1},"end":{"line":9,"column":1}},"children":[{"type":"text","value":"RadarOnly_QPE_24H_00.00","position":{"start":{"line":9,"column":1},"end":{"line":9,"column":1}},"key":"ZGaB5S2vUD"}],"key":"Lv3AAiqJPW"},{"type":"tableCell","position":{"start":{"line":9,"column":1},"end":{"line":9,"column":1}},"children":[{"type":"text","value":"Radar precipitation accumulation 24-hour","position":{"start":{"line":9,"column":1},"end":{"line":9,"column":1}},"key":"kFuMHxAFDC"}],"key":"w7z41rflpI"}],"key":"ALgdei3OtW"},{"type":"tableRow","position":{"start":{"line":10,"column":1},"end":{"line":10,"column":1}},"children":[{"type":"tableCell","position":{"start":{"line":10,"column":1},"end":{"line":10,"column":1}},"children":[{"type":"text","value":"MergedReflectivityQCComposite_00.50","position":{"start":{"line":10,"column":1},"end":{"line":10,"column":1}},"key":"glujcu7ap6"}],"key":"xN9ppSPGzd"},{"type":"tableCell","position":{"start":{"line":10,"column":1},"end":{"line":10,"column":1}},"children":[{"type":"text","value":"Composite Reflectivity Mosaic (optimal method)","position":{"start":{"line":10,"column":1},"end":{"line":10,"column":1}},"key":"Zt4ZUJ5tYM"}],"key":"trPUMISqzX"}],"key":"u2rjJh0TrD"},{"type":"tableRow","position":{"start":{"line":11,"column":1},"end":{"line":11,"column":1}},"children":[{"type":"tableCell","position":{"start":{"line":11,"column":1},"end":{"line":11,"column":1}},"children":[{"type":"text","value":"MultiSensor_QPE_12H_Pass1_00.00","position":{"start":{"line":11,"column":1},"end":{"line":11,"column":1}},"key":"nhVFAyhWZ9"}],"key":"JWFLneK9Ia"},{"type":"tableCell","position":{"start":{"line":11,"column":1},"end":{"line":11,"column":1}},"children":[{"type":"text","value":"Multi-sensor accumulation 12-hour (1-hour latency)","position":{"start":{"line":11,"column":1},"end":{"line":11,"column":1}},"key":"nNUGuQFNaN"}],"key":"pFawXdW64P"}],"key":"o368bEpTkd"},{"type":"tableRow","position":{"start":{"line":12,"column":1},"end":{"line":12,"column":1}},"children":[{"type":"tableCell","position":{"start":{"line":12,"column":1},"end":{"line":12,"column":1}},"children":[{"type":"text","value":"POSH_00.50\"","position":{"start":{"line":12,"column":1},"end":{"line":12,"column":1}},"key":"cjRRx2CHJK"}],"key":"g6JxniEjze"},{"type":"tableCell","position":{"start":{"line":12,"column":1},"end":{"line":12,"column":1}},"children":[{"type":"text","value":"Prob of Severe Hail","position":{"start":{"line":12,"column":1},"end":{"line":12,"column":1}},"key":"E7ojF5qkDi"}],"key":"D294v30hKP"}],"key":"dpSHQVCEcn"},{"type":"tableRow","position":{"start":{"line":13,"column":1},"end":{"line":13,"column":1}},"children":[{"type":"tableCell","position":{"start":{"line":13,"column":1},"end":{"line":13,"column":1}},"children":[{"type":"text","value":"CREF_1HR_MAX_00.50","position":{"start":{"line":13,"column":1},"end":{"line":13,"column":1}},"key":"RmtrhJlkgB"}],"key":"q6aSsRtDXP"},{"type":"tableCell","position":{"start":{"line":13,"column":1},"end":{"line":13,"column":1}},"children":[{"type":"text","value":"Composite Reflectivity Hourly Maximum","position":{"start":{"line":13,"column":1},"end":{"line":13,"column":1}},"key":"msWTBd1atK"}],"key":"YZPzsBxriu"}],"key":"F8JhkQkD8m"},{"type":"tableRow","position":{"start":{"line":14,"column":1},"end":{"line":14,"column":1}},"children":[{"type":"tableCell","position":{"start":{"line":14,"column":1},"end":{"line":14,"column":1}},"children":[{"type":"text","value":"PrecipRate_00.00","position":{"start":{"line":14,"column":1},"end":{"line":14,"column":1}},"key":"TVv1V6LJAk"}],"key":"OpkykSuN3Y"},{"type":"tableCell","position":{"start":{"line":14,"column":1},"end":{"line":14,"column":1}},"children":[{"type":"text","value":"Radar Precipitation Rate","position":{"start":{"line":14,"column":1},"end":{"line":14,"column":1}},"key":"qhpXt4KXUy"}],"key":"BNbFoxFdck"}],"key":"uBmyTz8pZ2"},{"type":"tableRow","position":{"start":{"line":15,"column":1},"end":{"line":15,"column":1}},"children":[{"type":"tableCell","position":{"start":{"line":15,"column":1},"end":{"line":15,"column":1}},"children":[{"type":"text","value":"MultiSensor_QPE_01H_Pass1_00.00","position":{"start":{"line":15,"column":1},"end":{"line":15,"column":1}},"key":"MWOryzVCyE"}],"key":"TxcxlsWc3r"},{"type":"tableCell","position":{"start":{"line":15,"column":1},"end":{"line":15,"column":1}},"children":[{"type":"text","value":"Multi-sensor accumulation 1-hour (1-hour latency)","position":{"start":{"line":15,"column":1},"end":{"line":15,"column":1}},"key":"eE2dKNjMuK"}],"key":"YcyChtC73L"}],"key":"IBSchWvNyk"},{"type":"tableRow","position":{"start":{"line":16,"column":1},"end":{"line":16,"column":1}},"children":[{"type":"tableCell","position":{"start":{"line":16,"column":1},"end":{"line":16,"column":1}},"children":[{"type":"text","value":"MultiSensor_QPE_01H_Pass2_00.00","position":{"start":{"line":16,"column":1},"end":{"line":16,"column":1}},"key":"G9yvymz6h5"}],"key":"pu2JtggStf"},{"type":"tableCell","position":{"start":{"line":16,"column":1},"end":{"line":16,"column":1}},"children":[{"type":"text","value":"Multi-sensor accumulation 1-hour (2-hour latency)","position":{"start":{"line":16,"column":1},"end":{"line":16,"column":1}},"key":"i1dcxDFzkl"}],"key":"kXvXgh62hU"}],"key":"NLuDZcpo1C"},{"type":"tableRow","position":{"start":{"line":17,"column":1},"end":{"line":17,"column":1}},"children":[{"type":"tableCell","position":{"start":{"line":17,"column":1},"end":{"line":17,"column":1}},"children":[{"type":"text","value":"RadarOnly_QPE_01H_00.00","position":{"start":{"line":17,"column":1},"end":{"line":17,"column":1}},"key":"OtCA775mbO"}],"key":"qBio64vZkl"},{"type":"tableCell","position":{"start":{"line":17,"column":1},"end":{"line":17,"column":1}},"children":[{"type":"text","value":"Radar precipitation accumulation 1-hour","position":{"start":{"line":17,"column":1},"end":{"line":17,"column":1}},"key":"HqU26zP94e"}],"key":"F1EZsHZD5q"}],"key":"qZqlMCqkc6"},{"type":"tableRow","position":{"start":{"line":18,"column":1},"end":{"line":18,"column":1}},"children":[{"type":"tableCell","position":{"start":{"line":18,"column":1},"end":{"line":18,"column":1}},"children":[{"type":"text","value":"LowLevelCompositeReflectivity","position":{"start":{"line":18,"column":1},"end":{"line":18,"column":1}},"key":"gXObufpVn1"}],"key":"zBOdzJERkH"},{"type":"tableCell","position":{"start":{"line":18,"column":1},"end":{"line":18,"column":1}},"children":[{"type":"text","value":"Low-Level Composite Reflectivity Mosaic (0-4km)","position":{"start":{"line":18,"column":1},"end":{"line":18,"column":1}},"key":"bQ4WzkCFnF"}],"key":"dIshyUX5at"}],"key":"iXKIyUeSKH"}],"key":"gTH1ms4qkP"}],"key":"rRHEyxhvod"},{"type":"block","kind":"notebook-content","children":[{"type":"thematicBreak","position":{"start":{"line":1,"column":1},"end":{"line":1,"column":1}},"key":"tDYraXmzlW"}],"key":"PeRMmlqrgH"},{"type":"block","kind":"notebook-content","children":[{"type":"heading","depth":2,"position":{"start":{"line":1,"column":1},"end":{"line":1,"column":1}},"children":[{"type":"text","value":"Summary","position":{"start":{"line":1,"column":1},"end":{"line":1,"column":1}},"key":"fbKra02Rfd"}],"identifier":"summary","label":"Summary","html_id":"summary","implicit":true,"key":"zZRfevj3Gl"},{"type":"paragraph","position":{"start":{"line":2,"column":1},"end":{"line":2,"column":1}},"children":[{"type":"text","value":"In summary, the MRMS System represents a robust and evolving platform that serves current research and operational needs, while paving ways for other innovations in decision-support services, aviation, transportation, numerical weather forecasting, hydrology, and public messaging.","position":{"start":{"line":2,"column":1},"end":{"line":2,"column":1}},"key":"b0UNlfZCOK"}],"key":"sVpL8fVX5z"},{"type":"heading","depth":4,"position":{"start":{"line":5,"column":1},"end":{"line":5,"column":1}},"children":[{"type":"text","value":"What’s next?","position":{"start":{"line":5,"column":1},"end":{"line":5,"column":1}},"key":"Upi5jRLQ9j"}],"identifier":"whats-next","label":"What’s next?","html_id":"whats-next","implicit":true,"key":"eZNvTrJr92"},{"type":"paragraph","position":{"start":{"line":6,"column":1},"end":{"line":6,"column":1}},"children":[{"type":"text","value":"In the following notebooks, you will be introduced to MRMS use case scenarios. We look into the March 2023 Rolling Fork, MS Tornado, the 2025 Texas Flood, and more!","position":{"start":{"line":6,"column":1},"end":{"line":6,"column":1}},"key":"eIwsJ55L9E"}],"key":"aiR6SpgJSE"}],"key":"f5zhQmfH6t"},{"type":"block","kind":"notebook-content","children":[{"type":"heading","depth":2,"position":{"start":{"line":1,"column":1},"end":{"line":1,"column":1}},"children":[{"type":"text","value":"Resources","position":{"start":{"line":1,"column":1},"end":{"line":1,"column":1}},"key":"xL4di4217d"}],"identifier":"resources","label":"Resources","html_id":"resources","implicit":true,"key":"GGWIpyiZbk"},{"type":"paragraph","position":{"start":{"line":2,"column":1},"end":{"line":2,"column":1}},"children":[{"type":"text","value":"To learn more about MRMS and its products, check out the links below!","position":{"start":{"line":2,"column":1},"end":{"line":2,"column":1}},"key":"loEWKBFnIy"}],"key":"nMIFwDxSh4"},{"type":"list","ordered":false,"spread":false,"position":{"start":{"line":4,"column":1},"end":{"line":15,"column":1}},"children":[{"type":"listItem","spread":true,"position":{"start":{"line":4,"column":1},"end":{"line":5,"column":1}},"children":[{"type":"paragraph","position":{"start":{"line":4,"column":1},"end":{"line":4,"column":1}},"children":[{"type":"link","url":"https://www.nssl.noaa.gov/about/events/review2021/presentations/NSSL2021LabReviewMRMS.pdf","position":{"start":{"line":4,"column":1},"end":{"line":4,"column":1}},"children":[{"type":"text","value":"Multi Radar Multi Sensor Overview","position":{"start":{"line":4,"column":1},"end":{"line":4,"column":1}},"key":"SDqyPJGMFm"}],"urlSource":"https://www.nssl.noaa.gov/about/events/review2021/presentations/NSSL2021LabReviewMRMS.pdf","key":"m1fVjIkYas"}],"key":"nNOFvyw6Zr"}],"key":"Y8iQogZMJ9"},{"type":"listItem","spread":true,"position":{"start":{"line":6,"column":1},"end":{"line":7,"column":1}},"children":[{"type":"paragraph","position":{"start":{"line":6,"column":1},"end":{"line":6,"column":1}},"children":[{"type":"link","url":"https://www.nssl.noaa.gov/projects/mrms/","position":{"start":{"line":6,"column":1},"end":{"line":6,"column":1}},"children":[{"type":"text","value":"NSSL Multi-Radar/Multi-Sensor System (MRMS)","position":{"start":{"line":6,"column":1},"end":{"line":6,"column":1}},"key":"ZjCh4dMmqU"}],"urlSource":"https://www.nssl.noaa.gov/projects/mrms/","key":"AP6r56UlHH"}],"key":"uFS4ScnWJ0"}],"key":"YJxh0yfTYj"},{"type":"listItem","spread":true,"position":{"start":{"line":8,"column":1},"end":{"line":10,"column":1}},"children":[{"type":"paragraph","position":{"start":{"line":8,"column":1},"end":{"line":8,"column":1}},"children":[{"type":"link","url":"https://www.nssl.noaa.gov/projects/mrms/operational/tables.php","position":{"start":{"line":8,"column":1},"end":{"line":8,"column":1}},"children":[{"type":"text","value":"Operational MRMS GRIB2 Table","position":{"start":{"line":8,"column":1},"end":{"line":8,"column":1}},"key":"EljCF0WhJn"}],"urlSource":"https://www.nssl.noaa.gov/projects/mrms/operational/tables.php","key":"ZTCWZZUT7U"}],"key":"afxlVBmToo"}],"key":"wIP2IQgis5"},{"type":"listItem","spread":true,"position":{"start":{"line":11,"column":1},"end":{"line":12,"column":1}},"children":[{"type":"paragraph","position":{"start":{"line":11,"column":1},"end":{"line":11,"column":1}},"children":[{"type":"link","url":"https://noaa-mrms-pds.s3.amazonaws.com/index.html","position":{"start":{"line":11,"column":1},"end":{"line":11,"column":1}},"children":[{"type":"text","value":"MRMS on AWS","position":{"start":{"line":11,"column":1},"end":{"line":11,"column":1}},"key":"x6FxUontIz"}],"urlSource":"https://noaa-mrms-pds.s3.amazonaws.com/index.html","key":"ebBC5GPXvr"}],"key":"Sfmw04IuLp"}],"key":"FeldcIK7gr"},{"type":"listItem","spread":true,"position":{"start":{"line":13,"column":1},"end":{"line":14,"column":1}},"children":[{"type":"paragraph","position":{"start":{"line":13,"column":1},"end":{"line":13,"column":1}},"children":[{"type":"link","url":"https://journals.ametsoc.org/view/journals/bams/97/9/bams-d-14-00173.1.xml","position":{"start":{"line":13,"column":1},"end":{"line":13,"column":1}},"children":[{"type":"text","value":"Article on MRMS Severe Weather and Aviation Products","position":{"start":{"line":13,"column":1},"end":{"line":13,"column":1}},"key":"l6INotB6im"}],"urlSource":"https://journals.ametsoc.org/view/journals/bams/97/9/bams-d-14-00173.1.xml","key":"BI2aD63IUD"}],"key":"khndFAXE12"}],"key":"k9Kvr0xlLl"},{"type":"listItem","spread":true,"position":{"start":{"line":15,"column":1},"end":{"line":15,"column":1}},"children":[{"type":"paragraph","position":{"start":{"line":15,"column":1},"end":{"line":15,"column":1}},"children":[{"type":"link","url":"https://journals.ametsoc.org/view/journals/bams/97/4/bams-d-14-00174.1.xml","position":{"start":{"line":15,"column":1},"end":{"line":15,"column":1}},"children":[{"type":"text","value":"Article on MRMS Quantitative Precipitation Estimates","position":{"start":{"line":15,"column":1},"end":{"line":15,"column":1}},"key":"tsWHXV72VD"}],"urlSource":"https://journals.ametsoc.org/view/journals/bams/97/4/bams-d-14-00174.1.xml","key":"Aa2IWha7Hk"}],"key":"rnnOhttkc9"}],"key":"XYHRcz8ctG"}],"key":"MqXj93aQ6Y"}],"key":"LrpsNGGEaO"}],"key":"mYgwTv2B9E"},"references":{"cite":{"order":[],"data":{}}},"footer":{"navigation":{"prev":{"title":"MRMS Cookbook","url":"/","group":"MRMS Cookbook"},"next":{"title":"Chapter 2: March 2023 Rolling Fork Tornado","url":"/notebooks/ch2-mar-2023-tornado-jdh","group":"MRMS Cookbook"}}},"domain":"http://localhost:3000"}